yalis/__init__.py
yalis-0.0.0.dist-info/METADATA
yalis-0.0.0.dist-info/WHEEL
yalis-0.0.0.dist-info/top_level.txt
yalis-0.0.0.dist-info/RECORD
